antibodies/__init__.py
antibodies/detect.py
antibodies_rafaelsandroni-0.0.1.dist-info/LICENSE
antibodies_rafaelsandroni-0.0.1.dist-info/METADATA
antibodies_rafaelsandroni-0.0.1.dist-info/WHEEL
antibodies_rafaelsandroni-0.0.1.dist-info/top_level.txt
antibodies_rafaelsandroni-0.0.1.dist-info/RECORD
