Metadata-Version: 2.1
Name: antibodies-rafaelsandroni
Version: 0.0.1
Summary: Antibodies for LLM hallucinations
Home-page: https://github.com/rafaelsandroni/antibodies
Author: rafaelsandroni
Author-email: rafael@metatext.io
Classifier: Programming Language :: Python :: 3
Classifier: License :: OSI Approved :: MIT License
Classifier: Operating System :: OS Independent
License-File: LICENSE
